[{"authors":["admin"],"categories":null,"content":"Experienced iOS developer with wide knowledge of other Apple platforms and strong focus on video and UI/UX related technologies. Msc background in Computer Science, plenty of experience working in different environments (enterprise, research lab, software agency, freelancing).\n","date":-62135596800,"expirydate":-62135596800,"kind":"taxonomy","lang":"en","lastmod":-62135596800,"objectID":"2525497d367e79493fd32b198b28f040","permalink":"https://petik3.github.io/authors/admin/","publishdate":"0001-01-01T00:00:00Z","relpermalink":"/authors/admin/","section":"authors","summary":"Experienced iOS developer with wide knowledge of other Apple platforms and strong focus on video and UI/UX related technologies. Msc background in Computer Science, plenty of experience working in different environments (enterprise, research lab, software agency, freelancing).","tags":null,"title":"Peter Huszák","type":"authors"}]